livid/__init__.py
livid-0.0.2.dist-info/METADATA
livid-0.0.2.dist-info/WHEEL
livid-0.0.2.dist-info/RECORD
